pulumi_onelogin/__init__.py
pulumi_onelogin/_inputs.py
pulumi_onelogin/_utilities.py
pulumi_onelogin/app.py
pulumi_onelogin/auth_servers.py
pulumi_onelogin/get_apps.py
pulumi_onelogin/get_auth_servers.py
pulumi_onelogin/get_auth_servers_claims.py
pulumi_onelogin/get_auth_servers_instance.py
pulumi_onelogin/get_auth_servers_scopes.py
pulumi_onelogin/get_mappings.py
pulumi_onelogin/get_privileges.py
pulumi_onelogin/get_privileges_instance.py
pulumi_onelogin/get_risk_rules.py
pulumi_onelogin/get_risk_rules_instance.py
pulumi_onelogin/outputs.py
pulumi_onelogin/privileges.py
pulumi_onelogin/provider.py
pulumi_onelogin/pulumi-plugin.json
pulumi_onelogin/py.typed
pulumi_onelogin/risk_rules.py
pulumi_onelogin/role.py
pulumi_onelogin/user.py
pulumi_onelogin/apps/__init__.py
pulumi_onelogin/apps/_inputs.py
pulumi_onelogin/apps/get_actions.py
pulumi_onelogin/apps/get_actions_values.py
pulumi_onelogin/apps/get_conditions.py
pulumi_onelogin/apps/get_conditions_operators.py
pulumi_onelogin/apps/get_instance.py
pulumi_onelogin/apps/get_rules.py
pulumi_onelogin/apps/get_rules_instance.py
pulumi_onelogin/apps/get_users.py
pulumi_onelogin/apps/outputs.py
pulumi_onelogin/apps/rules.py
pulumi_onelogin/config/__init__.py
pulumi_onelogin/config/__init__.pyi
pulumi_onelogin/config/outputs.py
pulumi_onelogin/config/vars.py
pulumi_onelogin/roles/__init__.py
pulumi_onelogin/roles/_inputs.py
pulumi_onelogin/roles/get_admins.py
pulumi_onelogin/roles/get_apps.py
pulumi_onelogin/roles/get_instance.py
pulumi_onelogin/roles/get_roles.py
pulumi_onelogin/roles/get_users.py
pulumi_onelogin/roles/outputs.py
pulumi_onelogin/users/__init__.py
pulumi_onelogin/users/_inputs.py
pulumi_onelogin/users/get_apps.py
pulumi_onelogin/users/get_devices.py
pulumi_onelogin/users/get_instance.py
pulumi_onelogin/users/get_users.py
pulumi_onelogin/users/get_v1.py
pulumi_onelogin/users/get_v1_apps.py
pulumi_onelogin/users/get_v1_instance.py
pulumi_onelogin/users/outputs.py
pulumi_onelogin/users/v1.py
pulumi_onelogin-0.6.9.dist-info/METADATA
pulumi_onelogin-0.6.9.dist-info/WHEEL
pulumi_onelogin-0.6.9.dist-info/top_level.txt
pulumi_onelogin-0.6.9.dist-info/RECORD
