Metadata-Version: 2.2
Name: pulumi_onelogin
Version: 0.6.9
Summary: A Pulumi package for creating and managing OneLogin cloud resources.
License: Apache-2.0
Project-URL: Homepage, https://pulumi.io
Project-URL: Repository, https://github.com/pulumi/pulumi-onelogin
Keywords: pulumi,onelogin
Requires-Python: >=3.9
Requires-Dist: parver>=0.2.1
Requires-Dist: pulumi<4.0.0,>=3.142.0
Requires-Dist: semver>=2.8.1
Requires-Dist: typing-extensions>=4.11; python_version < "3.11"
